{
  "flow": {
    "dependencies": {},
    "id": "88",
    "jobs": {"command_ls": {
      "endTime": "2011-01-07T21:30:49.013-08:00",
      "id": "88",
      "name": "command_ls",
      "overrideProps": {
        "azkaban.flow.id": "88",
        "azkaban.flow.start.day": "07",
        "azkaban.flow.start.hour": "21",
        "azkaban.flow.start.milliseconds": "946",
        "azkaban.flow.start.minute": "30",
        "azkaban.flow.start.month": "01",
        "azkaban.flow.start.seconds": "48",
        "azkaban.flow.start.timestamp": "2011-01-07T21:30:48.946-08:00",
        "azkaban.flow.start.timezone": "America/Los_Angeles",
        "azkaban.flow.start.year": "2011",
        "azkaban.flow.uuid": "2ce01404-fa13-48ec-b594-d9de0722fe1c"
      },
      "returnProps": {},
      "startTime": "2011-01-07T21:30:48.951-08:00",
      "status": "SUCCEEDED",
      "type": "jobManagerLoaded"
    }},
    "root": ["command_ls"]
  },
  "parentProps": {
    "azkaban.flow.id": "88",
    "azkaban.flow.start.day": "07",
    "azkaban.flow.start.hour": "21",
    "azkaban.flow.start.milliseconds": "946",
    "azkaban.flow.start.minute": "30",
    "azkaban.flow.start.month": "01",
    "azkaban.flow.start.seconds": "48",
    "azkaban.flow.start.timestamp": "2011-01-07T21:30:48.946-08:00",
    "azkaban.flow.start.timezone": "America/Los_Angeles",
    "azkaban.flow.start.year": "2011",
    "azkaban.flow.uuid": "2ce01404-fa13-48ec-b594-d9de0722fe1c"
  },
  "type": "FlowExecutionHolder"
}